cookbooks/data_refinement/refinement.py
cookbooks/grader_validation/accuracy.py
cookbooks/grader_validation/grader_validator.py
cookbooks/grader_validation/rewardbench2.py
cookbooks/integrations/langsmith.py
cookbooks/pairwise_evaluation/pairwise_evaluation.py
cookbooks/training_judge_model/bradley-terry/dataset.py
cookbooks/training_judge_model/bradley-terry/trainer.py
cookbooks/training_judge_model/grpo/chat_rl_dataset.py
cookbooks/training_judge_model/grpo/pairwise/reward_fn.py
cookbooks/training_judge_model/grpo/pointwise/reward_fn.py
cookbooks/zero_shot_evaluation/__main__.py
cookbooks/zero_shot_evaluation/chart_generator.py
cookbooks/zero_shot_evaluation/query_generator.py
cookbooks/zero_shot_evaluation/report_generator.py
cookbooks/zero_shot_evaluation/response_collector.py
cookbooks/zero_shot_evaluation/schema.py
cookbooks/zero_shot_evaluation/zero_shot_pipeline.py
openjudge/__init__.py
openjudge/analyzer/__init__.py
openjudge/analyzer/base_analyzer.py
openjudge/analyzer/pairwise_analyzer.py
openjudge/analyzer/statistical/__init__.py
openjudge/analyzer/statistical/consistency_analyzer.py
openjudge/analyzer/statistical/distribution_analyzer.py
openjudge/analyzer/validation/__init__.py
openjudge/analyzer/validation/accuracy_analyzer.py
openjudge/analyzer/validation/base_validation_analyzer.py
openjudge/analyzer/validation/correlation_analyzer.py
openjudge/analyzer/validation/f1_score_analyzer.py
openjudge/analyzer/validation/false_negative_analyzer.py
openjudge/analyzer/validation/false_positive_analyzer.py
openjudge/analyzer/validation/precision_analyzer.py
openjudge/analyzer/validation/recall_analyzer.py
openjudge/generator/__init__.py
openjudge/generator/base_generator.py
openjudge/generator/llm_grader_generator.py
openjudge/generator/iterative_rubric/__init__.py
openjudge/generator/iterative_rubric/categorizer.py
openjudge/generator/iterative_rubric/generator.py
openjudge/generator/iterative_rubric/mcr_selector.py
py_openjudge-0.2.1.dist-info/licenses/LICENSE
py_openjudge-0.2.1.dist-info/METADATA
py_openjudge-0.2.1.dist-info/WHEEL
py_openjudge-0.2.1.dist-info/top_level.txt
py_openjudge-0.2.1.dist-info/RECORD
